stratesticPlus/backtesting/__init__.py
stratesticPlus/backtesting/_mixin.py
stratesticPlus/backtesting/combining/__init__.py
stratesticPlus/backtesting/combining/_combining.py
stratesticPlus/backtesting/helpers/__init__.py
stratesticPlus/backtesting/helpers/evaluation/__init__.py
stratesticPlus/backtesting/helpers/evaluation/_constants.py
stratesticPlus/backtesting/helpers/evaluation/_results.py
stratesticPlus/backtesting/helpers/evaluation/metrics.py
stratesticPlus/backtesting/helpers/margin/__init__.py
stratesticPlus/backtesting/helpers/margin/_margin.py
stratesticPlus/backtesting/helpers/plotting/__init__.py
stratesticPlus/backtesting/helpers/plotting/_plotting.py
stratesticPlus/backtesting/helpers/trade.py
stratesticPlus/backtesting/iterative/__init__.py
stratesticPlus/backtesting/iterative/_iterative.py
stratesticPlus/backtesting/optimization/__init__.py
stratesticPlus/backtesting/optimization/_optimization.py
stratesticPlus/backtesting/vectorized/__init__.py
stratesticPlus/backtesting/vectorized/_vectorized.py
stratesticPlus/forwardtesting/forwardtesting.py
stratesticPlus/strategies/__init__.py
stratesticPlus/strategies/_mixin.py
stratesticPlus/strategies/ichimoku/__init__.py
stratesticPlus/strategies/ichimoku/ichimoku.py
stratesticPlus/strategies/machine_learning/__init__.py
stratesticPlus/strategies/machine_learning/helpers/__init__.py
stratesticPlus/strategies/machine_learning/helpers/_defaults.py
stratesticPlus/strategies/machine_learning/helpers/_evaluation.py
stratesticPlus/strategies/machine_learning/helpers/_feature_engineering.py
stratesticPlus/strategies/machine_learning/helpers/_helpers.py
stratesticPlus/strategies/machine_learning/helpers/_pipeline_custom_classes.py
stratesticPlus/strategies/machine_learning/helpers/_training.py
stratesticPlus/strategies/machine_learning/machine_learning.py
stratesticPlus/strategies/machine_learning/models/__init__.py
stratesticPlus/strategies/mean_reversion/__init__.py
stratesticplus-1.1.2.dist-info/license.txt
stratesticplus-1.1.2.dist-info/METADATA
stratesticplus-1.1.2.dist-info/WHEEL
stratesticplus-1.1.2.dist-info/RECORD
